daemonflux/__init__.py
daemonflux/flux.py
daemonflux/utils.py
daemonflux-0.8.2.dist-info/LICENSE
daemonflux-0.8.2.dist-info/METADATA
daemonflux-0.8.2.dist-info/WHEEL
daemonflux-0.8.2.dist-info/top_level.txt
daemonflux-0.8.2.dist-info/RECORD
