Metadata-Version: 2.1
Name: daemonflux
Version: 0.8.2
Summary: Tabulated representation of a muon-calibrated muon and neutrino flux model
Home-page: https://github.com/mceq-project/daemonflux
Download-URL: https://pypi.python.org/pypi/daemonflux
Author: Anatoli Fedynitch
Maintainer-email: afedynitch@gmail.com
License: BSD 3-Clause License
Classifier: Development Status :: 4 - Beta
Classifier: Topic :: Scientific/Engineering :: Physics
Classifier: Intended Audience :: Science/Research
Classifier: Programming Language :: Python
Classifier: Programming Language :: Python :: 3
Classifier: Programming Language :: Python :: 3.8
Classifier: Programming Language :: Python :: 3.9
Classifier: Programming Language :: Python :: 3.10
Classifier: Programming Language :: Python :: 3.11
Classifier: Programming Language :: Python :: 3.12
Classifier: License :: OSI Approved :: BSD License
Classifier: License :: OSI Approved :: GNU Library or Lesser General Public License (LGPL)
Requires-Python: >=3.8
License-File: LICENSE
Requires-Dist: numpy
Requires-Dist: scipy >=1.8.0
Requires-Dist: rich
Provides-Extra: examples
Requires-Dist: matplotlib ; extra == 'examples'
Provides-Extra: test
Requires-Dist: pytest ; extra == 'test'
